LICENSE.txt
MANIFEST.in
README.md
setup.cfg
setup.py
certbot_s3front/__init__.py
certbot_s3front/authenticator.py
certbot_s3front/installer.py
certbot_s3front.egg-info/PKG-INFO
certbot_s3front.egg-info/SOURCES.txt
certbot_s3front.egg-info/dependency_links.txt
certbot_s3front.egg-info/entry_points.txt
certbot_s3front.egg-info/requires.txt
certbot_s3front.egg-info/top_level.txt