Metadata-Version: 1.1
Name: certbot-s3front
Version: 0.2.0
Summary: S3/CloudFront plugin for Certbot client
Home-page: https://github.com/dlapiduz/certbot-s3front
Author: Diego Lapiduz
Author-email: diego@lapiduz.com
License: MIT
Keywords: certbot,cloudfront,s3
Platform: UNKNOWN
Classifier: Development Status :: 3 - Alpha
Classifier: Environment :: Plugins
Classifier: Intended Audience :: System Administrators
Classifier: License :: OSI Approved :: Apache Software License
Classifier: Operating System :: POSIX :: Linux
Classifier: Programming Language :: Python
Classifier: Programming Language :: Python :: 2
Classifier: Programming Language :: Python :: 2.6
Classifier: Programming Language :: Python :: 2.7
Classifier: Topic :: Internet :: WWW/HTTP
Classifier: Topic :: Security
Classifier: Topic :: System :: Installation/Setup
Classifier: Topic :: System :: Networking
Classifier: Topic :: System :: Systems Administration
Classifier: Topic :: Utilities
